asn1tools_ext/__init__.py
asn1tools_ext/codecs/__init__.py
asn1tools_ext/codecs/ber.py
asn1tools_ext/codecs/compiler.py
asn1tools_ext/codecs/constraints_checker.py
asn1tools_ext/codecs/der.py
asn1tools_ext/codecs/gser.py
asn1tools_ext/codecs/jer.py
asn1tools_ext/codecs/oer.py
asn1tools_ext/codecs/per.py
asn1tools_ext/codecs/permitted_alphabet.py
asn1tools_ext/codecs/type_checker.py
asn1tools_ext/codecs/uper.py
asn1tools_ext/codecs/xer.py
asn1tools_ext/compiler.py
asn1tools_ext/errors.py
asn1tools_ext/parser.py
asn1tools_ext/source/__init__.py
asn1tools_ext/source/c/__init__.py
asn1tools_ext/source/c/oer.py
asn1tools_ext/source/c/oer_functions.py
asn1tools_ext/source/c/uper.py
asn1tools_ext/source/c/uper_functions.py
asn1tools_ext/source/c/utils.py
asn1tools_ext/source/rust/__init__.py
asn1tools_ext/source/rust/uper.py
asn1tools_ext/source/rust/utils.py
asn1tools_ext/version.py
asn1tools_ext-0.2.2.dist-info/licenses/LICENSE
asn1tools_ext-0.2.2.dist-info/WHEEL
asn1tools_ext-0.2.2.dist-info/METADATA
asn1tools_ext-0.2.2.dist-info/RECORD
