Metadata-Version: 2.4
Name: asn1tools_ext
Version: 0.2.2
Summary: ASN.1 parser, compiler and general swiss army knife
Author: xadaemon
Author-email: xadaemon <mxavier@ccho.eu>
License-File: LICENSE
Classifier: Development Status :: 4 - Beta
Classifier: Intended Audience :: Developers
Classifier: License :: OSI Approved :: MIT License
Classifier: Programming Language :: Python :: 3
Classifier: Topic :: Software Development :: Libraries :: Python Modules
Requires-Dist: pyparsing>=3.2.5
Requires-Dist: bitstruct>=8.21.0
Requires-Python: >=3.13
Project-URL: source, https://github.com/xadaemon/asn1tools-ext
